shop_scraper_hr/__init__.py
shop_scraper_hr/common.py
shop_scraper_hr/scrapers/__init__.py
shop_scraper_hr/scrapers/konzum.py
shop_scraper_hr/scrapers/tommy.py
shop_scraper_hr-0.1.1.dist-info/METADATA
shop_scraper_hr-0.1.1.dist-info/WHEEL
shop_scraper_hr-0.1.1.dist-info/RECORD
