Metadata-Version: 2.1
Name: shop-scraper-hr
Version: 0.1.1
Summary: Scraper for prices of goods in Croatian supermarkets
License: GPL-3.0-or-later
Author: JCGoran
Author-email: jcgoran@protonmail.com
Requires-Python: >=3.9,<4.0
Classifier: License :: OSI Approved :: GNU General Public License v3 or later (GPLv3+)
Classifier: Programming Language :: Python :: 3
Classifier: Programming Language :: Python :: 3.9
Classifier: Programming Language :: Python :: 3.10
Classifier: Programming Language :: Python :: 3.11
Requires-Dist: beautifulsoup4 (>=4.12.2,<5.0.0)
Requires-Dist: requests (>=2.31.0,<3.0.0)
